{"filename":"C:\\Users\\lab_services_student\\source\\repos\\EventEase\\__azurite_db_blob__.json","collections":[{"name":"$SERVICES_COLLECTION$","data":[],"idIndex":null,"binaryIndices":{},"constraints":null,"uniqueNames":["accountName"],"transforms":{},"objType":"$SERVICES_COLLECTION$","dirty":false,"cachedIndex":null,"cachedBinaryIndex":null,"cachedData":null,"adaptiveBinaryIndices":true,"transactional":false,"cloneObjects":false,"cloneMethod":"parse-stringify","asyncListeners":false,"disableMeta":false,"disableChangesApi":true,"disableDeltaChangesApi":true,"autoupdate":false,"serializableIndices":true,"disableFreeze":true,"ttl":null,"maxId":0,"DynamicViews":[],"events":{"insert":[],"update":[],"pre-insert":[],"pre-update":[],"close":[],"flushbuffer":[],"error":[],"delete":[null],"warning":[null]},"changes":[],"dirtyIds":[]},{"name":"$CONTAINERS_COLLECTION$","data":[{"accountName":"devstoreaccount1","name":"venue-images","properties":{"etag":"\"0x1DAD2B34ACD7360\"","lastModified":"2026-05-07T16:05:05.730Z","leaseStatus":"unlocked","leaseState":"available","hasImmutabilityPolicy":false,"hasLegalHold":false},"meta":{"revision":0,"created":1778169905762,"version":0},"$loki":1}],"idIndex":null,"binaryIndices":{"accountName":{"name":"accountName","dirty":false,"values":[0]},"name":{"name":"name","dirty":false,"values":[0]}},"constraints":null,"uniqueNames":[],"transforms":{},"objType":"$CONTAINERS_COLLECTION$","dirty":false,"cachedIndex":null,"cachedBinaryIndex":null,"cachedData":null,"adaptiveBinaryIndices":true,"transactional":false,"cloneObjects":false,"cloneMethod":"parse-stringify","asyncListeners":false,"disableMeta":false,"disableChangesApi":true,"disableDeltaChangesApi":true,"autoupdate":false,"serializableIndices":true,"disableFreeze":true,"ttl":null,"maxId":1,"DynamicViews":[],"events":{"insert":[],"update":[],"pre-insert":[],"pre-update":[],"close":[],"flushbuffer":[],"error":[],"delete":[null],"warning":[null]},"changes":[],"dirtyIds":[]},{"name":"$BLOBS_COLLECTION$","data":[{"accountName":"devstoreaccount1","containerName":"venue-images","name":"2ab320ce-ee06-404b-b978-2ac65710a09b.jpg","properties":{"creationTime":"2026-05-07T16:06:49.426Z","lastModified":"2026-05-07T16:06:49.426Z","etag":"\"0x1BE041C40CCB810\"","contentLength":8166,"contentType":"image/jpeg","contentMD5":{"type":"Buffer","data":[225,165,70,96,198,237,255,205,26,198,190,194,93,234,185,95]},"blobType":"BlockBlob","leaseStatus":"unlocked","leaseState":"available","serverEncrypted":true,"accessTier":"Hot","accessTierInferred":true,"accessTierChangeTime":"2026-05-07T16:06:49.426Z"},"snapshot":"","isCommitted":true,"persistency":{"id":"97b3ff28-fff5-402c-aae6-d2ce40e079ec","offset":0,"count":8166},"meta":{"revision":0,"created":1778170009453,"version":0},"$loki":1},{"deleted":false,"accountName":"devstoreaccount1","containerName":"venue-images","name":"40c77c65-993e-4d3a-bc56-3a0d243a9b5a.jpg","properties":{"creationTime":"2026-05-07T19:33:50.674Z","lastModified":"2026-05-07T19:33:50.674Z","etag":"\"0x236C6980A99BC20\"","contentLength":8166,"contentType":"image/jpeg","contentMD5":{"type":"Buffer","data":[225,165,70,96,198,237,255,205,26,198,190,194,93,234,185,95]},"blobType":"BlockBlob","leaseStatus":"unlocked","leaseState":"available","serverEncrypted":true,"accessTier":"Hot","accessTierInferred":true,"accessTierChangeTime":"2026-05-07T19:33:50.674Z"},"snapshot":"","isCommitted":true,"persistency":{"id":"a04d4692-eaac-4fe0-9e41-66276f447d79","offset":0,"count":8166},"meta":{"revision":0,"created":1778182430697,"version":0},"$loki":3},{"deleted":false,"accountName":"devstoreaccount1","containerName":"venue-images","name":"2a507e41-501d-4fa8-95a8-a5d315b950de.jpg","properties":{"creationTime":"2026-05-07T19:37:16.978Z","lastModified":"2026-05-07T19:37:16.978Z","etag":"\"0x25F6BFB7C37C0C0\"","contentLength":8166,"contentType":"image/jpeg","contentMD5":{"type":"Buffer","data":[225,165,70,96,198,237,255,205,26,198,190,194,93,234,185,95]},"blobType":"BlockBlob","leaseStatus":"unlocked","leaseState":"available","serverEncrypted":true,"accessTier":"Hot","accessTierInferred":true,"accessTierChangeTime":"2026-05-07T19:37:16.978Z"},"snapshot":"","isCommitted":true,"persistency":{"id":"a04d4692-eaac-4fe0-9e41-66276f447d79","offset":8166,"count":8166},"meta":{"revision":0,"created":1778182636988,"version":0},"$loki":4}],"idIndex":null,"binaryIndices":{"accountName":{"name":"accountName","dirty":false,"values":[2,1,0]},"containerName":{"name":"containerName","dirty":false,"values":[2,1,0]},"name":{"name":"name","dirty":false,"values":[2,0,1]},"snapshot":{"name":"snapshot","dirty":false,"values":[2,1,0]}},"constraints":null,"uniqueNames":[],"transforms":{},"objType":"$BLOBS_COLLECTION$","dirty":false,"cachedIndex":null,"cachedBinaryIndex":null,"cachedData":null,"adaptiveBinaryIndices":true,"transactional":false,"cloneObjects":false,"cloneMethod":"parse-stringify","asyncListeners":false,"disableMeta":false,"disableChangesApi":true,"disableDeltaChangesApi":true,"autoupdate":false,"serializableIndices":true,"disableFreeze":true,"ttl":null,"maxId":4,"DynamicViews":[],"events":{"insert":[],"update":[],"pre-insert":[],"pre-update":[],"close":[],"flushbuffer":[],"error":[],"delete":[null],"warning":[null]},"changes":[],"dirtyIds":[]},{"name":"$BLOCKS_COLLECTION$","data":[],"idIndex":null,"binaryIndices":{"accountName":{"name":"accountName","dirty":false,"values":[]},"containerName":{"name":"containerName","dirty":false,"values":[]},"blobName":{"name":"blobName","dirty":false,"values":[]},"name":{"name":"name","dirty":false,"values":[]}},"constraints":null,"uniqueNames":[],"transforms":{},"objType":"$BLOCKS_COLLECTION$","dirty":false,"cachedIndex":null,"cachedBinaryIndex":null,"cachedData":null,"adaptiveBinaryIndices":true,"transactional":false,"cloneObjects":false,"cloneMethod":"parse-stringify","asyncListeners":false,"disableMeta":false,"disableChangesApi":true,"disableDeltaChangesApi":true,"autoupdate":false,"serializableIndices":true,"disableFreeze":true,"ttl":null,"maxId":0,"DynamicViews":[],"events":{"insert":[],"update":[],"pre-insert":[],"pre-update":[],"close":[],"flushbuffer":[],"error":[],"delete":[null],"warning":[null]},"changes":[],"dirtyIds":[]}],"databaseVersion":1.5,"engineVersion":1.5,"autosave":true,"autosaveInterval":5000,"autosaveHandle":null,"throttledSaves":true,"options":{"persistenceMethod":"fs","autosave":true,"autosaveInterval":5000,"serializationMethod":"normal","destructureDelimiter":"$<\n"},"persistenceMethod":"fs","persistenceAdapter":null,"verbose":false,"events":{"init":[null],"loaded":[],"flushChanges":[],"close":[],"changes":[],"warning":[]},"ENV":"NODEJS"}